Workbook
Name rendimento_investimento: App!$D$10:$D$10

Sheet App
B8: CONFIGURAÇÕES
B9: Salário | D9: 2500
B10: Rendimento Carteira | D10: 0.006
B11: Sugestão de Investimento (30%) | D11: =D9*30% -> 750
B14: INVESTIMENTO MENSAL
B16: Quanto Investir por mês? | D16: 750
B17: Por Quantos Anos ? | D17: 5
B18: Taxa de Rendimento mensal? | D18: 0.01079
B19: Patrimônio Acumulado ? | D19: =FV(D18,D17*12,-D16) -> 62832.685
B20: Dividendo Mensais ? | D20: =D19*$D$10 -> 376.99611
B22: Cenários | D22: Dividendo
A23: 2 | B23: Quanto em 2 Anos? | C23: =FV($D$18,$A23*12,-$D$16) -> 20420.72 | D23: =C23*$D$10 -> 122.52432
A24: 5 | B24: Quanto em 5 Anos? | C24: =FV($D$18,$A24*12,-$D$16) -> 62832.685 | D24: =C24*$D$10 -> 376.99611
A25: 10 | B25: Quanto em 10 Anos? | C25: =FV($D$18,$A25*12,-$D$16) -> 182463.16 | D25: =C25*$D$10 -> 1094.779
A26: 20 | B26: Quanto em 20 Anos? | C26: =FV($D$18,$A26*12,-$D$16) -> 843898.8 | D26: =C26*$D$10 -> 5063.3928
A27: 30 | B27: Quanto em 30 Anos? | C27: =FV($D$18,$A27*12,-$D$16) -> 3241627.2 | D27: =C27*$D$10 -> 19449.763
B30: PERFIL | C30: AGRESSIVO
B31: VALOR A SER INVESTIDO POR MÊS | C31: =D16 -> 750
B33: TIPO DE FII | C33: Percentual Sugerido | D33: Valores
B35: PAPEL | C35: =VLOOKUP($C$30&"-"&B35,apoio!$A2:$D22,4,FALSE) -> 0.5 | D35: =C35*$C$31 -> 375
B36: TIJOLO | C36: =VLOOKUP($C$30&"-"&B36,apoio!$A3:$D23,4,FALSE) -> 0.1 | D36: =C36*$C$31 -> 75
B37: HIBRIDOS | C37: =VLOOKUP($C$30&"-"&B37,apoio!$A4:$D24,4,FALSE) -> 0.05 | D37: =C37*$C$31 -> 37.5
B38: FOFs | C38: =VLOOKUP($C$30&"-"&B38,apoio!$A5:$D25,4,FALSE) -> 0.05 | D38: =C38*$C$31 -> 37.5
B39: DESENVOLVIMENTO | C39: =VLOOKUP($C$30&"-"&B39,apoio!$A6:$D26,4,FALSE) -> 0.2 | D39: =C39*$C$31 -> 150
B40: HOTELARIAS | C40: =VLOOKUP($C$30&"-"&B40,apoio!$A7:$D27,4,FALSE) -> 0.1 | D40: =C40*$C$31 -> 75
D41: =SUM(D35:D40) -> 750

Sheet apoio
A2: chave | B2: PERFIL | C2: TIPO DE FII
A3: =$B$3&"-"&C3 -> CONSERVADOR-PAPEL | B3: CONSERVADOR | C3: PAPEL | D3: 0.3
A4: =$B$3&"-"&C4 -> CONSERVADOR-TIJOLO | B4: CONSERVADOR | C4: TIJOLO | D4: 0.5
A5: =$B$3&"-"&C5 -> CONSERVADOR-HIBRIDOS | B5: CONSERVADOR | C5: HIBRIDOS | D5: 0.1
A6: =$B$3&"-"&C6 -> CONSERVADOR-FOFs | B6: CONSERVADOR | C6: FOFs | D6: 0.1
A7: =$B$3&"-"&C7 -> CONSERVADOR-DESENVOLVIMENTO | B7: CONSERVADOR | C7: DESENVOLVIMENTO | D7: 0
A8: =$B$3&"-"&C8 -> CONSERVADOR-HOTELARIAS | B8: CONSERVADOR | C8: HOTELARIAS | D8: 0
A10: =$B$10&"-"&C10 -> MODERADO -PAPEL | B10: MODERADO | C10: PAPEL | D10: 0.32
A11: =$B$10&"-"&C11 -> MODERADO -TIJOLO | B11: MODERADO | C11: TIJOLO | D11: 0.4
A12: =$B$10&"-"&C12 -> MODERADO -HIBRIDOS | B12: MODERADO | C12: HIBRIDOS | D12: 0.08
A13: =$B$10&"-"&C13 -> MODERADO -FOFs | B13: MODERADO | C13: FOFs | D13: 0.1
A14: =$B$10&"-"&C14 -> MODERADO -DESENVOLVIMENTO | B14: MODERADO | C14: DESENVOLVIMENTO | D14: 0.05
A15: =$B$10&"-"&C15 -> MODERADO -HOTELARIAS | B15: MODERADO | C15: HOTELARIAS | D15: 0.05
A17: =$B$17&"-"&C17 -> AGRESSIVO-PAPEL | B17: AGRESSIVO | C17: PAPEL | D17: 0.5
A18: =$B$17&"-"&C18 -> AGRESSIVO-TIJOLO | B18: AGRESSIVO | C18: TIJOLO | D18: 0.1
A19: =$B$17&"-"&C19 -> AGRESSIVO-HIBRIDOS | B19: AGRESSIVO | C19: HIBRIDOS | D19: 0.05
A20: =$B$17&"-"&C20 -> AGRESSIVO-FOFs | B20: AGRESSIVO | C20: FOFs | D20: 0.05
A21: =$B$17&"-"&C21 -> AGRESSIVO-DESENVOLVIMENTO | B21: =$B$17&"-"&D21 -> AGRESSIVO-0,2 | C21: DESENVOLVIMENTO | D21: 0.2
A22: =$B$17&"-"&C22 -> AGRESSIVO-HOTELARIAS | B22: AGRESSIVO | C22: HOTELARIAS | D22: 0.1
